{
  "asOf": "2026-07-17",
  "updatedAt": "2026-07-17T08:32:11.533Z",
  "source": "tencent-gtimg",
  "quotes": {
    "600585": {
      "currentPrice": 17.67,
      "asOf": "2026-07-17"
    },
    "600690": {
      "currentPrice": 20.95,
      "asOf": "2026-07-17"
    },
    "600941": {
      "currentPrice": 93.4,
      "asOf": "2026-07-17"
    },
    "600999": {
      "currentPrice": 18.92,
      "asOf": "2026-07-17"
    },
    "601318": {
      "currentPrice": 50.7,
      "asOf": "2026-07-17"
    },
    "601600": {
      "currentPrice": 8.44,
      "asOf": "2026-07-17"
    },
    "601601": {
      "currentPrice": 29.75,
      "asOf": "2026-07-17"
    },
    "603605": {
      "currentPrice": 56.73,
      "asOf": "2026-07-17"
    },
    "002027": {
      "currentPrice": 5,
      "asOf": "2026-07-17"
    },
    "002049": {
      "currentPrice": 64.1,
      "asOf": "2026-07-17"
    },
    "000333": {
      "currentPrice": 82.71,
      "asOf": "2026-07-17"
    },
    "000001": {
      "currentPrice": 10.78,
      "asOf": "2026-07-17"
    }
  }
}
